jsonpointer_helpers/__init__.py
jsonpointer_helpers-0.2.0.dist-info/LICENSE
jsonpointer_helpers-0.2.0.dist-info/WHEEL
jsonpointer_helpers-0.2.0.dist-info/METADATA
jsonpointer_helpers-0.2.0.dist-info/RECORD
